dapla_metadata/__init__.py
dapla_metadata/_shared/__init__.py
dapla_metadata/_shared/config.py
dapla_metadata/_shared/enums.py
dapla_metadata/_shared/py.typed
dapla_metadata/dapla/__init__.py
dapla_metadata/dapla/user_info.py
dapla_metadata/datasets/__init__.py
dapla_metadata/datasets/_merge.py
dapla_metadata/datasets/code_list.py
dapla_metadata/datasets/core.py
dapla_metadata/datasets/dapla_dataset_path_info.py
dapla_metadata/datasets/dataset_parser.py
dapla_metadata/datasets/model_validation.py
dapla_metadata/datasets/py.typed
dapla_metadata/datasets/statistic_subject_mapping.py
dapla_metadata/datasets/compatibility/__init__.py
dapla_metadata/datasets/compatibility/_handlers.py
dapla_metadata/datasets/compatibility/_utils.py
dapla_metadata/datasets/compatibility/model_backwards_compatibility.py
dapla_metadata/datasets/external_sources/__init__.py
dapla_metadata/datasets/external_sources/external_sources.py
dapla_metadata/datasets/utility/__init__.py
dapla_metadata/datasets/utility/constants.py
dapla_metadata/datasets/utility/enums.py
dapla_metadata/datasets/utility/urn.py
dapla_metadata/datasets/utility/utils.py
dapla_metadata/standards/__init__.py
dapla_metadata/standards/name_validator.py
dapla_metadata/standards/standard_validators.py
dapla_metadata/standards/utils/__init__.py
dapla_metadata/standards/utils/constants.py
dapla_metadata/variable_definitions/__init__.py
dapla_metadata/variable_definitions/exceptions.py
dapla_metadata/variable_definitions/vardef.py
dapla_metadata/variable_definitions/vardok_id.py
dapla_metadata/variable_definitions/vardok_vardef_id_pair.py
dapla_metadata/variable_definitions/variable_definition.py
dapla_metadata/variable_definitions/_generated/.openapi-generator-ignore
dapla_metadata/variable_definitions/_generated/README.md
dapla_metadata/variable_definitions/_generated/__init__.py
dapla_metadata/variable_definitions/_generated/.openapi-generator/FILES
dapla_metadata/variable_definitions/_generated/.openapi-generator/VERSION
dapla_toolbelt_metadata-0.12.0.dist-info/METADATA
dapla_toolbelt_metadata-0.12.0.dist-info/WHEEL
dapla_toolbelt_metadata-0.12.0.dist-info/licenses/LICENSE
dapla_toolbelt_metadata-0.12.0.dist-info/RECORD
