Metadata-Version: 2.4
Name: dapla-toolbelt-metadata
Version: 0.12.0
Summary: Dapla Toolbelt Metadata
Project-URL: Changelog, https://github.com/statisticsnorway/dapla-toolbelt-metadata/releases
Project-URL: Documentation, https://statisticsnorway.github.io/dapla-toolbelt-metadata
Project-URL: Homepage, https://github.com/statisticsnorway/dapla-toolbelt-metadata
Project-URL: Repository, https://github.com/statisticsnorway/dapla-toolbelt-metadata
Author-email: Statistics Norway <metadata@ssb.no>
Maintainer-email: "Division for Data Enablement (724)" <metadata@ssb.no>
License-Expression: MIT
License-File: LICENSE
Classifier: Development Status :: 4 - Beta
Classifier: Programming Language :: Python :: 3.10
Classifier: Programming Language :: Python :: 3.11
Classifier: Programming Language :: Python :: 3.12
Classifier: Programming Language :: Python :: 3.13
Classifier: Programming Language :: Python :: 3.14
Classifier: Typing :: Typed
Requires-Python: >=3.10
Requires-Dist: arrow>=1.3.0
Requires-Dist: beautifulsoup4>=4.12.3
Requires-Dist: dapla-auth-client>=1.2.1; python_version > '3.10'
Requires-Dist: gcsfs>=2023.1.0
Requires-Dist: google-auth>=2.38.0
Requires-Dist: lxml>=5.3.1
Requires-Dist: pandas>=2.3.3
Requires-Dist: pyarrow>=8.0.0
Requires-Dist: pydantic>=2.5.2
Requires-Dist: pyjwt>=2.8.0
Requires-Dist: python-dateutil>=2.9.0.post0
Requires-Dist: python-dotenv>=1.0.1
Requires-Dist: pytz>=2025.2
Requires-Dist: requests>=2.31.0
Requires-Dist: ruamel-yaml>=0.18.10
Requires-Dist: ssb-datadoc-model==8.0.0
Requires-Dist: ssb-klass-python>=1.0.1
Requires-Dist: typing-extensions>=4.12.2
Requires-Dist: universal-pathlib>=0.3.0
Requires-Dist: urllib3>=2.5.0
